reqto/__init__.py
reqto/example.py
reqto/reqto.py
reqto/core/__init__.py
reqto/core/reqto.py
reqto-0.1.7.dist-info/LICENSE
reqto-0.1.7.dist-info/METADATA
reqto-0.1.7.dist-info/WHEEL
reqto-0.1.7.dist-info/top_level.txt
reqto-0.1.7.dist-info/RECORD
