Metadata-Version: 2.1
Name: reqto
Version: 0.1.7
Summary: A wrapper around requests to tackle unstable timeout issues
Home-page: https://github.com/DovaX/reqto
Author: DovaX
Author-email: dovax.ai@gmail.com
License: UNKNOWN
Platform: UNKNOWN
Classifier: Programming Language :: Python :: 3
Classifier: License :: OSI Approved :: MIT License
Classifier: Operating System :: OS Independent
Requires-Python: >=3.6
License-File: LICENSE
Requires-Dist: eventlet
Requires-Dist: requests
